README
setup.cfg
setup.py
thrift_http_tornado/__init__.py
thrift_http_tornado/server.py
thrift_http_tornado/transport.py
thrift_http_tornado.egg-info/PKG-INFO
thrift_http_tornado.egg-info/SOURCES.txt
thrift_http_tornado.egg-info/dependency_links.txt
thrift_http_tornado.egg-info/requires.txt
thrift_http_tornado.egg-info/top_level.txt