Metadata-Version: 1.0
Name: thrift-http-tornado
Version: 0.1.3
Summary: Thirft transport implementation over the HTTP protocol
Home-page: https://github.com/upfluence/thrift-http-tornado
Author: Alexis Montagne
Author-email: alexis.montagne@upfluence.co
License: UNKNOWN
Platform: UNKNOWN
